mathset/__init__.py
mathset/mathset.py
mathset-1.0.4.dist-info/METADATA
mathset-1.0.4.dist-info/WHEEL
mathset-1.0.4.dist-info/licenses/LICENSE
mathset-1.0.4.dist-info/RECORD
