Metadata-Version: 2.1
Name: mathset
Version: 1.0.4
Summary: mathset is a Python module allowing user to perform basic mathematical operations on finite sets
Project-URL: Homepage, https://kakrzysiek.github.io/mathset
Project-URL: Source, https://github.com/KaKrzysiek/mathset
Author-email: Krzysztof Karczewski <kakrzysiek13@gmail.com>
License-File: LICENSE
Classifier: License :: OSI Approved :: Mozilla Public License 2.0 (MPL 2.0)
Classifier: Operating System :: OS Independent
Classifier: Programming Language :: Python :: 3
Requires-Python: >=3.10
